lightbench/CIFAR100.py
lightbench/CIFAR10_wide.py
lightbench/MNIST.py
lightbench/SVHN.py
lightbench/Tolstoi_RNN.py
lightbench/__init__.py
lightbench/__main__.py
lightbench/absolute_varying_scale.py
lightbench/adversarial_gradient.py
lightbench/batch_size_scaling.py
lightbench/beale.py
lightbench/benchmark_matrix.png
lightbench/benchmark_results.md
lightbench/class_imbalance_rare.py
lightbench/constrained_optimization_log.py
lightbench/constrained_optimization_relu.py
lightbench/create_hiker_analogy_diagram.py
lightbench/discontinuous_gradient.py
lightbench/dynamic_landscape.py
lightbench/exploding_gradient.py
lightbench/format_results.py
lightbench/generalization_summod.py
lightbench/generalization_weighted_summod.py
lightbench/generate_animations.py
lightbench/gradient_delay.py
lightbench/gradient_noise_scale_heavy_tailed.py
lightbench/gradient_noise_scale_instantaneous_brown.py
lightbench/gradient_noise_scale_temporal_brown.py
lightbench/gradient_noise_scale_white.py
lightbench/grokking.py
lightbench/ill_conditioned.py
lightbench/ill_conditioned_mismatched.py
lightbench/layer_wise_scale.py
lightbench/loss_contour.py
lightbench/memory_constrained.py
lightbench/merge_logs.py
lightbench/minimax.py
lightbench/momentum_utilization.py
lightbench/multi_objective_pareto.py
lightbench/noisy_matmul.py
lightbench/non_markovian.py
lightbench/parameter_scale.py
lightbench/plasticity_summod.py
lightbench/plasticity_weighted_summod.py
lightbench/plateau_navigation.py
lightbench/powers.py
lightbench/powers_varying_target.py
lightbench/quadratic_coupled.py
lightbench/quadratic_flip.py
lightbench/quadratic_outliers.py
lightbench/quadratic_quantization_aware_training.py
lightbench/quadratic_quantized_gradient.py
lightbench/quadratic_sparse.py
lightbench/quadratic_varying_scale.py
lightbench/quadratic_varying_target.py
lightbench/rastrigin.py
lightbench/relu_boundaries.py
lightbench/rosenbrock.py
lightbench/run_all_benchmarks.py
lightbench/saddle_point.py
lightbench-0.1.0.dist-info/METADATA
lightbench-0.1.0.dist-info/WHEEL
lightbench-0.1.0.dist-info/entry_points.txt
lightbench-0.1.0.dist-info/top_level.txt
lightbench-0.1.0.dist-info/RECORD
