Metadata-Version: 2.4
Name: lightbench
Version: 0.1.0
Summary: Benchmark suite for HeavyBall optimizers
Author-email: LightBench Authors <github.lightbench@nestler.sh>
Project-URL: Source, https://github.com/HomebrewML/LightBench
Classifier: License :: OSI Approved :: BSD License
Classifier: Intended Audience :: Science/Research
Classifier: Programming Language :: Python :: 3
Classifier: Topic :: Scientific/Engineering :: Artificial Intelligence
Requires-Python: >=3.9
Requires-Dist: heavyball>=2.0.0
Requires-Dist: torch<3.0,>=2.1.0
Requires-Dist: numpy<2.0,>=1.26.0
Requires-Dist: typer>=0.17.4
Requires-Dist: optuna>=4.5.0
Requires-Dist: optunahub>=0.3.1
Requires-Dist: lightgbm>=4.6.0
Requires-Dist: threadpoolctl>=3.6.0
Requires-Dist: scipy>=1.16.2
Requires-Dist: scikit-learn>=1.6.1
Requires-Dist: numexpr>=2.10.2
Requires-Dist: pymoo>=0.6.1
Requires-Dist: cmaes>=0.12.0
Provides-Extra: dev
Requires-Dist: matplotlib>=3.7.0; extra == "dev"
Requires-Dist: seaborn>=0.12.0; extra == "dev"
Requires-Dist: pandas>=1.5.0; extra == "dev"
Requires-Dist: tabulate>=0.9.0; extra == "dev"
Requires-Dist: termcolor>=2.1.0; extra == "dev"
Requires-Dist: typer[all]; extra == "dev"
Requires-Dist: pytest>=8.3.0; extra == "dev"
